wechat_web_auth/__init__.py
wechat_web_auth/exceptions.py
wechat_web_auth/wechat.py
wechat_web_auth-0.1.1.dist-info/DESCRIPTION.rst
wechat_web_auth-0.1.1.dist-info/METADATA
wechat_web_auth-0.1.1.dist-info/metadata.json
wechat_web_auth-0.1.1.dist-info/RECORD
wechat_web_auth-0.1.1.dist-info/top_level.txt
wechat_web_auth-0.1.1.dist-info/WHEEL
