Metadata-Version: 2.0
Name: wechat-web-auth
Version: 0.1.1
Summary: 微信公众平台网页授权获取用户信息python封装
Home-page: https://github.com/jinuljt/wechat-web-auth
Author: Juntao Liu
Author-email: jinuljt@gmail.com
License: MIT License
Keywords: wechat,web auth
Platform: any
Requires-Dist: requests
